qt_web_bridge/__init__.py
qt_web_bridge/bridge.py
qt_web_bridge/panel.py
qt_web_bridge/utils.py
qt_web_bridge/webview.py
qt_web_bridge/temp/__init__.py
soren_n_qt_web_bridge-1.1.10.dist-info/METADATA
soren_n_qt_web_bridge-1.1.10.dist-info/WHEEL
soren_n_qt_web_bridge-1.1.10.dist-info/RECORD
