Metadata-Version: 2.4
Name: soren-n-qt-web-bridge
Version: 1.1.10
Summary: Clean Qt WebView widgets for hosting modern web UIs without styling conflicts
Project-URL: Homepage, https://github.com/soren-n/qt-web-bridge
Project-URL: Repository, https://github.com/soren-n/qt-web-bridge.git
Project-URL: Issues, https://github.com/soren-n/qt-web-bridge/issues
Project-URL: Documentation, https://qt-web-bridge.readthedocs.io/
Author-email: Soren N <soren@example.com>
License: GPL-3.0-or-later
Keywords: bridge,javascript,pyside6,qt,qtpy,webview
Classifier: Development Status :: 4 - Beta
Classifier: Intended Audience :: Developers
Classifier: License :: OSI Approved :: GNU General Public License v3 or later (GPLv3+)
Classifier: Programming Language :: Python :: 3
Classifier: Programming Language :: Python :: 3.11
Classifier: Programming Language :: Python :: 3.12
Classifier: Topic :: Software Development :: Libraries :: Python Modules
Classifier: Topic :: Software Development :: User Interfaces
Requires-Python: >=3.11
Requires-Dist: qtpy>=2.0.0
Provides-Extra: docs
Requires-Dist: furo>=2024.1.29; extra == 'docs'
Requires-Dist: myst-parser>=2.0.0; extra == 'docs'
Requires-Dist: sphinx-autoapi>=3.0.0; extra == 'docs'
Requires-Dist: sphinx-autodoc-typehints>=1.25.0; extra == 'docs'
Requires-Dist: sphinx-copybutton>=0.5.2; extra == 'docs'
Requires-Dist: sphinx-design>=0.5.0; extra == 'docs'
Requires-Dist: sphinx>=7.1.0; extra == 'docs'
Requires-Dist: sphinxext-opengraph>=0.9.0; extra == 'docs'
Provides-Extra: examples
Requires-Dist: pyside6>=6.0; extra == 'examples'
